[
  {
    "name": "lucky_looser",
    "rating": 1627,
    "sets": 146,
    "sets_won": 111,
    "prev_rating": 1627
  },
  {
    "name": "klicunou",
    "rating": 1599,
    "sets": 68,
    "sets_won": 50,
    "prev_rating": 1639
  },
  {
    "name": "drapegnik",
    "rating": 1464,
    "sets": 37,
    "sets_won": 23,
    "prev_rating": 1464
  },
  {
    "name": "bg_grab",
    "rating": 1422,
    "sets": 98,
    "sets_won": 36,
    "prev_rating": 1422
  },
  {
    "name": "rubanau",
    "rating": 1398,
    "sets": 23,
    "sets_won": 11,
    "prev_rating": 1373
  },
  {
    "name": "vladdeykun",
    "rating": 1393,
    "sets": 19,
    "sets_won": 8,
    "prev_rating": 1393
  },
  {
    "name": "lisouski",
    "rating": 1364,
    "sets": 7,
    "sets_won": 1,
    "prev_rating": 1364
  },
  {
    "name": "unikalas",
    "rating": 1318,
    "sets": 45,
    "sets_won": 14,
    "prev_rating": 1303
  },
  {
    "name": "uladbohdan",
    "rating": 1293,
    "sets": 26,
    "sets_won": 5,
    "prev_rating": 1293
  },
  {
    "name": "iraborsch",
    "rating": 1122,
    "sets": 63,
    "sets_won": 7,
    "prev_rating": 1122
  }
]
